bia_rembi_models/__init__.py
bia_rembi_models/acquisition.py
bia_rembi_models/analysis.py
bia_rembi_models/correlation.py
bia_rembi_models/sample.py
bia_rembi_models/specimen.py
bia_rembi_models/study.py
bia_rembi_models/study_component.py
bia_rembi_models-0.1.0.dist-info/LICENSE
bia_rembi_models-0.1.0.dist-info/WHEEL
bia_rembi_models-0.1.0.dist-info/METADATA
bia_rembi_models-0.1.0.dist-info/RECORD
