Metadata-Version: 2.1
Name: bia-rembi-models
Version: 0.1.0
Summary: 
Author: Matthew Hartley
Author-email: matthewh@ebi.ac.uk
Requires-Python: >=3.9,<4.0
Classifier: Programming Language :: Python :: 3
Classifier: Programming Language :: Python :: 3.9
Classifier: Programming Language :: Python :: 3.10
Classifier: Programming Language :: Python :: 3.11
Requires-Dist: pydantic (>=1.10.2,<2.0.0)
